action_set
